CHANGELOG
LICENSE
MANIFEST.in
README
setup.py
dragonkeeper/__init__.py
dragonkeeper/common.py
dragonkeeper/dragonkeeper.py
dragonkeeper/favicon.ico
dragonkeeper/httpconnection.py
dragonkeeper/httpscopeinterface.py
dragonkeeper/maps.py
dragonkeeper/simpleserver.py
dragonkeeper/stpconnection.py
dragonkeeper/stpwebsocket.py
dragonkeeper/utils.py
dragonkeeper/websocket.py
dragonkeeper.egg-info/PKG-INFO
dragonkeeper.egg-info/SOURCES.txt
dragonkeeper.egg-info/dependency_links.txt
dragonkeeper.egg-info/entry_points.txt
dragonkeeper.egg-info/top_level.txt