Metadata-Version: 1.0
Name: dragonkeeper
Version: 0.8.3
Summary: An HTTP proxy for Opera Dragonfly development
Home-page: http://bitbucket.org/scope/dragonkeeper/
Author: Christian Krebs, Rune Halvorsen, Jan Borsodi
Author-email: chrisk@opera.com, runeh@opera.com, jborsodi@opera.com
License: UNKNOWN
Platform: UNKNOWN
